{
    "start": "2023-01-28T01:37:05.246Z",
    "end": "2023-01-28T01:37:18.581Z",
    "capabilities": {
        "acceptInsecureCerts": true,
        "browserName": "chrome",
        "browserVersion": "109.0.5414.120",
        "chrome": {
            "chromedriverVersion": "109.0.5414.74 (e7c5703604daa9cc128ccf5a5d3e993513758913-refs/branch-heads/5414@{#1172})",
            "userDataDir": "C:\\Users\\ORHAN~1.DEM\\AppData\\Local\\Temp\\scoped_dir36128_236790067"
        },
        "goog:chromeOptions": {
            "debuggerAddress": "localhost:49257"
        },
        "networkConnectionEnabled": false,
        "pageLoadStrategy": "normal",
        "platformName": "windows",
        "proxy": {},
        "setWindowRect": true,
        "strictFileInteractability": false,
        "timeouts": {
            "implicit": 0,
            "pageLoad": 300000,
            "script": 30000
        },
        "unhandledPromptBehavior": "dismiss and notify",
        "webauthn:extension:credBlob": true,
        "webauthn:extension:largeBlob": true,
        "webauthn:virtualAuthenticators": true,
        "sessionId": "c4e9336e04aefa35e28850322b41f8eb"
    },
    "host": "localhost",
    "port": 9515,
    "baseUrl": "https://stage.biobright.xyz",
    "framework": "mocha",
    "suites": [
        {
            "name": "login form",
            "duration": 11894,
            "start": "2023-01-28T01:37:06.647Z",
            "end": "2023-01-28T01:37:18.541Z",
            "sessionId": "c4e9336e04aefa35e28850322b41f8eb",
            "tests": [
                {
                    "name": "should verify `Summary` page displays on successful login - C367",
                    "start": "2023-01-28T01:37:06.648Z",
                    "end": "2023-01-28T01:37:18.538Z",
                    "duration": 11890,
                    "state": "passed"
                },
                {
                    "name": "TC2 - C368",
                    "start": "2023-01-28T01:37:06.648Z",
                    "end": "2023-01-28T01:37:18.538Z",
                    "duration": 11890,
                    "state": "fail"
                }
            ],
            "hooks": []
        },
        {
            "name": "suite 2",
            "duration": 11894,
            "start": "2023-01-28T01:37:06.647Z",
            "end": "2023-01-28T01:37:18.541Z",
            "sessionId": "c4e9336e04aefa35e28850322b41f8eb",
            "tests": [
                {
                    "name": "TC-3",
                    "start": "2023-01-28T01:37:06.648Z",
                    "end": "2023-01-28T01:37:18.538Z",
                    "duration": 11890,
                    "state": "passed"
                },
                {
                    "name": "TC4",
                    "start": "2023-01-28T01:37:06.648Z",
                    "end": "2023-01-28T01:37:18.538Z",
                    "duration": 11890,
                    "state": "fail"
                }
            ],
            "hooks": []
        }
    ],
    "specs": [
        "C:\\Users\\orhan.demirci\\webdriverio-test\\test\\specs\\1-login.spec.js"
    ],
    "state": {
        "passed": 1,
        "failed": 1,
        "skipped": 0
    }
}